rawl/__init__.py
rawl-0.3.5.dist-info/LICENSE
rawl-0.3.5.dist-info/METADATA
rawl-0.3.5.dist-info/WHEEL
rawl-0.3.5.dist-info/top_level.txt
rawl-0.3.5.dist-info/RECORD
