Metadata-Version: 2.1
Name: rawl
Version: 0.3.5
Summary: An ugly raw SQL postgresql db layer
Home-page: https://github.com/mikeshultz/rawl
Author: Mike Shultz
Author-email: mike@mikeshultz.com
License: UNKNOWN
Keywords: postgresql database bindings sql
Platform: UNKNOWN
Classifier: Development Status :: 4 - Beta
Classifier: Intended Audience :: Developers
Classifier: Topic :: Database
Classifier: License :: OSI Approved :: GNU General Public License v3 or later (GPLv3+)
Classifier: Programming Language :: Python :: 3.5
Classifier: Programming Language :: Python :: 3.6
Requires-Dist: psycopg2 (>=2.7.3.2)
